{
    "fluentMethods": true,
    "relationships": [
        {
            "relationshipType": "one-to-one",
            "relationshipValidateRules": "required",
            "relationshipName": "user",
            "otherEntityName": "user",
            "otherEntityField": "login",
            "ownerSide": true,
            "otherEntityRelationshipName": "userSettings"
        }
    ],
    "fields": [
        {
            "fieldName": "usdRate",
            "fieldType": "Double",
            "fieldValidateRules": [
                "required"
            ]
        },
        {
            "fieldName": "sarRate",
            "fieldType": "Double",
            "fieldValidateRules": [
                "required"
            ]
        }
    ],
    "changelogDate": "20171209040531",
    "entityTableName": "user_settings",
    "dto": "mapstruct",
    "pagination": "no",
    "service": "serviceImpl",
    "jpaMetamodelFiltering": false
}